FTNPACKBOT/__init__.py
FNTPACKBOT-1.0.3.dist-info/METADATA
FNTPACKBOT-1.0.3.dist-info/WHEEL
FNTPACKBOT-1.0.3.dist-info/top_level.txt
FNTPACKBOT-1.0.3.dist-info/RECORD
