Metadata-Version: 2.1
Name: FNTPACKBOT
Version: 1.0.3
Summary: Lobby bot.
Home-page: https://www.youtube.com/channel/UCiDx7oYO4f0qbDEzGdgaq_w?view_as=subscriber&pbjreload=101
Author: Bryna
Author-email: UNKNOWN
License: UNKNOWN
Platform: UNKNOWN
Classifier: Programming Language :: Python :: 3
Classifier: License :: OSI Approved :: MIT License
Classifier: Operating System :: OS Independent
Requires-Dist: BenBotAsync
Requires-Dist: FortniteAPIAsync
Requires-Dist: aiohttp
Requires-Dist: crayons
Requires-Dist: fortnitepy
Requires-Dist: sanic
Requires-Dist: uvloop
